ps/herald/__init__.py
ps/herald/angular_api.py
ps/herald/bare_html_api.py
ps/herald/database.py
ps/herald/model.py
ps/herald/ps_bridge.py
ps/herald/ps_herald.py
ps/herald/ps_neelix.py
ps/herald/graph_ql/__init__.py
ps/herald/graph_ql/mutation.py
ps/herald/graph_ql/query.py
ps/herald/graph_ql/schema.py
ps/herald/graph_ql/typedefs.py
ps/herald/static/angular_api/favicon.ico
ps/herald/static/angular_api/main.js
ps/herald/static/angular_api/main.js.map
ps/herald/static/angular_api/polyfills.js
ps/herald/static/angular_api/polyfills.js.map
ps/herald/static/angular_api/runtime.js
ps/herald/static/angular_api/runtime.js.map
ps/herald/static/angular_api/styles.css
ps/herald/static/angular_api/styles.css.map
ps/herald/static/angular_api/vendor.js
ps/herald/static/angular_api/vendor.js.map
ps/herald/static/bare_html/favicon-16x16.png
ps/herald/static/bare_html/favicon.ico
ps/herald/static/bare_html/loading.gif
ps/herald/static/bare_html/logging_server.css
ps/herald/static/bare_html/favicon/android-icon-144x144.png
ps/herald/static/bare_html/favicon/android-icon-192x192.png
ps/herald/static/bare_html/favicon/android-icon-36x36.png
ps/herald/static/bare_html/favicon/android-icon-48x48.png
ps/herald/static/bare_html/favicon/android-icon-72x72.png
ps/herald/static/bare_html/favicon/android-icon-96x96.png
ps/herald/static/bare_html/favicon/apple-icon-114x114.png
ps/herald/static/bare_html/favicon/apple-icon-120x120.png
ps/herald/static/bare_html/favicon/apple-icon-144x144.png
ps/herald/static/bare_html/favicon/apple-icon-152x152.png
ps/herald/static/bare_html/favicon/apple-icon-180x180.png
ps/herald/static/bare_html/favicon/apple-icon-57x57.png
ps/herald/static/bare_html/favicon/apple-icon-60x60.png
ps/herald/static/bare_html/favicon/apple-icon-72x72.png
ps/herald/static/bare_html/favicon/apple-icon-76x76.png
ps/herald/static/bare_html/favicon/apple-icon-precomposed.png
ps/herald/static/bare_html/favicon/apple-icon.png
ps/herald/static/bare_html/favicon/browserconfig.xml
ps.herald-1.4.2.dist-info/METADATA
ps.herald-1.4.2.dist-info/WHEEL
ps.herald-1.4.2.dist-info/entry_points.txt
ps.herald-1.4.2.dist-info/top_level.txt
ps.herald-1.4.2.dist-info/RECORD
