Metadata-Version: 2.1
Name: ps.herald
Version: 1.4.2
Summary: UNKNOWN
Home-page: https://bitbucket.org/drsetz/ps.herald
Author: Setz
Author-email: Thomas.Setz@acm.org
License: "License :: OSI Approved :: GNU General Public License (GPL)
Keywords: PS
Platform: UNKNOWN
Classifier: Development Status :: 4 - Beta
Classifier: Intended Audience :: Developers
Classifier: Operating System :: MacOS
Classifier: Operating System :: POSIX
Classifier: Operating System :: Microsoft :: Windows
Classifier: Programming Language :: Python :: 3.9
Classifier: Topic :: Software Development
Classifier: Topic :: Utilities
Requires-Dist: Flask
Requires-Dist: click
Requires-Dist: flask-sqlalchemy
Requires-Dist: graphene
Requires-Dist: graphene-sqlalchemy
Requires-Dist: flask-graphql
Requires-Dist: flask-cors
Requires-Dist: ps.basic
